Workbook

Sheet Summary
A1: Day-Case Improvement Summary
A2: Formula cells are highlighted in yellow; assumption cells are highlighted in green.
A3: Measure | B3: Low | C3: High | D3: Formula / note
A4: Current baseline | B4: =Inputs!B6 | C4: =Inputs!B6 | D4: Current day-case rate supplied: 67.9%
A5: What if | B5: =Inputs!B7 | C5: =Inputs!B7 | D5: Move to national median: 85.7%
A6: Rate improvement | B6: ='Worked Calculation'!B7 | C6: ='Worked Calculation'!B7 | D6: Target rate - current rate
A7: Converted cases | B7: ='Worked Calculation'!B10 | C7: ='Worked Calculation'!B10 | D7: Eligible cohort x rate improvement
A8: Avoided bed days | B8: ='Worked Calculation'!B14 | C8: ='Worked Calculation'!B15 | D8: Low uses 1 bed day; high uses 2.18 bed days
A9: Financial efficiency opportunity | B9: ='Worked Calculation'!B16 | C9: ='Worked Calculation'!B17 | D9: Avoided bed days x GBP350
A10: Waiting list impact | B10: ='Worked Calculation'!B19 | C10: ='Worked Calculation'!B20 | D10: Low is no automatic reduction; high assumes capacity is reinvested
A11: Income potential | B11: ='Worked Calculation'!B24 | C11: ='Worked Calculation'!B25 | D11: Only if released capacity is used for additional activity

Sheet Inputs
A1: Inputs
A2: Formula cells are highlighted in yellow; assumption cells are highlighted in green.
A3: Input | B3: Value | C3: Source / note
A4: Opening RTT backlog | B4: 23086 | C4: Backlog baseline used in previous opportunity tables
A5: Eligible case cohort | B5: 14700 | C5: Example surgical/HVLC cohort used in the day-case scenario
A6: Current day-case rate | B6: 0.679 | C6: Scenario baseline supplied: 67.9%
A7: Target day-case rate | B7: 0.857 | C7: National median supplied: 85.7%
A8: Bed-day cost | B8: 350 | C8: Cost avoidance assumption: GBP350 per bed day
A9: Low bed days avoided per conversion | B9: 1 | C9: Minimum assumption
A10: High bed days avoided per conversion | B10: 2.18 | C10: Observed ordinary elective LoS proxy used for high case
A11: Source income value from previous utilisation model | B11: 577787 | C11: Definition: total extra-case income value (£577,787) from the user-shared utilisation/cash-up model. It is used only as an indicative gross income basis for extra cases/procedures, not as a confirmed tariff or a staff-cost saving.
A12: Source extra cases from same previous model | B12: 5539 | C12: Definition: extra-case volume (5,539) attached to the same source income value. This keeps the income numerator and case denominator from the same source scenario.
A13: Derived income per additional case proxy | B13: =B11/B12 | C13: Definition: average indicative income per extra case = £577,787 / 5,539 = c.£104.31. This is a proxy used only for income potential where additional activity is delivered; it should be replaced with an agreed tariff, income or contribution value if Finance provides one.

Sheet Worked Calculation
A1: Worked Day-Case Calculation
A2: Formula cells are highlighted in yellow; assumption cells are highlighted in green.
A3: Step | B3: Value | C3: Formula / explanation
A4: Eligible case cohort | B4: =Inputs!B5 | C4: Input
A5: Current day-case rate | B5: =Inputs!B6 | C5: Input
A6: Target day-case rate | B6: =Inputs!B7 | C6: Input
A7: Rate improvement | B7: =B6-B5 | C7: Target rate - current rate
A8: Current day cases | B8: =B4*B5 | C8: Eligible cohort x current rate
A9: Target day cases | B9: =B4*B6 | C9: Eligible cohort x target rate
A10: Converted overnight cases / additional day cases | B10: =B4*B7 | C10: Eligible cohort x rate improvement
A11: Bed-day cost | B11: =Inputs!B8 | C11: Input
A12: Low bed days avoided per conversion | B12: =Inputs!B9 | C12: Input
A13: High bed days avoided per conversion | B13: =Inputs!B10 | C13: Input
A14: Low avoided bed days | B14: =B10*B12 | C14: Converted cases x low bed-day assumption
A15: High avoided bed days | B15: =B10*B13 | C15: Converted cases x high bed-day assumption
A16: Financial efficiency low | B16: =B14*B11 | C16: Low avoided bed days x GBP350
A17: Financial efficiency high | B17: =B15*B11 | C17: High avoided bed days x GBP350
A18: Opening RTT backlog | B18: =Inputs!B4 | C18: Input
A19: Waiting list impact low | B19: =0 | C19: No automatic RTT reduction unless released capacity is reinvested
A20: Waiting list impact high | B20: =B10 | C20: One converted case creates capacity for one RTT pathway
A21: Backlog reduction high % | B21: =B20/B18 | C21: Waiting list impact high / opening backlog
A22: Closing backlog high | B22: =B18-B20 | C22: Opening backlog - waiting list impact high
A23: Income per case proxy | B23: =Inputs!B13 | C23: Derived proxy: source income value (£577,787) divided by source extra cases (5,539), giving c.£104.31 per additional case.
A24: Income potential low | B24: =0 | C24: No additional activity delivered
A25: Income potential high | B25: =B10*B23 | C25: Shifted / additional cases x derived income per case proxy. This is a gross income-potential lens only and applies only if capacity is used to deliver extra activity.

Sheet Specialty View
A1: FY25/26 Day-Case Rate by Specialty
A2: Formula cells are highlighted in yellow; assumption cells are highlighted in green.
A3: Specialty | B3: Focus surgical/HVLC | C3: Eligible elective spells | D3: Day cases | E3: Ordinary elective | F3: Day-case rate | G3: Gap to 85.7% | H3: Addl day cases to 85.7%
A4: General Surgery | B4: Yes | C4: 4728 | D4: 3900 | E4: =C4-D4 | F4: =D4/C4 | G4: =Inputs!B7-F4 | H4: =MAX(0,ROUND(C4*G4,0))
A5: Clinical Haematology | B5: No | C5: 4433 | D5: 4428 | E5: =C5-D5 | F5: =D5/C5 | G5: =Inputs!B7-F5 | H5: =MAX(0,ROUND(C5*G5,0))
A6: Gastroenterology | B6: No | C6: 3732 | D6: 3664 | E6: =C6-D6 | F6: =D6/C6 | G6: =Inputs!B7-F6 | H6: =MAX(0,ROUND(C6*G6,0))
A7: Medical Oncology | B7: No | C7: 3718 | D7: 3710 | E7: =C7-D7 | F7: =D7/C7 | G7: =Inputs!B7-F7 | H7: =MAX(0,ROUND(C7*G7,0))
A8: Trauma & Orthopaedics | B8: Yes | C8: 2156 | D8: 916 | E8: =C8-D8 | F8: =D8/C8 | G8: =Inputs!B7-F8 | H8: =MAX(0,ROUND(C8*G8,0))
A9: Urology | B9: Yes | C9: 1889 | D9: 1180 | E9: =C9-D9 | F9: =D9/C9 | G9: =Inputs!B7-F9 | H9: =MAX(0,ROUND(C9*G9,0))
A10: Clinical Oncology | B10: No | C10: 1675 | D10: 1667 | E10: =C10-D10 | F10: =D10/C10 | G10: =Inputs!B7-F10 | H10: =MAX(0,ROUND(C10*G10,0))
A11: Ophthalmology | B11: Yes | C11: 1454 | D11: 1447 | E11: =C11-D11 | F11: =D11/C11 | G11: =Inputs!B7-F11 | H11: =MAX(0,ROUND(C11*G11,0))
A12: Diagnostic Imaging Service | B12: No | C12: 1331 | D12: 1311 | E12: =C12-D12 | F12: =D12/C12 | G12: =Inputs!B7-F12 | H12: =MAX(0,ROUND(C12*G12,0))
A13: Gynaecology | B13: Yes | C13: 1328 | D13: 800 | E13: =C13-D13 | F13: =D13/C13 | G13: =Inputs!B7-F13 | H13: =MAX(0,ROUND(C13*G13,0))
A14: Cardiology | B14: No | C14: 1180 | D14: 1150 | E14: =C14-D14 | F14: =D14/C14 | G14: =Inputs!B7-F14 | H14: =MAX(0,ROUND(C14*G14,0))
A15: Obstetrics Service | B15: No | C15: 1093 | D15: 2 | E15: =C15-D15 | F15: =D15/C15 | G15: =Inputs!B7-F15 | H15: =MAX(0,ROUND(C15*G15,0))
A16: ENT | B16: Yes | C16: 978 | D16: 897 | E16: =C16-D16 | F16: =D16/C16 | G16: =Inputs!B7-F16 | H16: =MAX(0,ROUND(C16*G16,0))
A17: Oral Surgery | B17: Yes | C17: 941 | D17: 898 | E17: =C17-D17 | F17: =D17/C17 | G17: =Inputs!B7-F17 | H17: =MAX(0,ROUND(C17*G17,0))
A18: Rheumatology | B18: No | C18: 537 | D18: 534 | E18: =C18-D18 | F18: =D18/C18 | G18: =Inputs!B7-F18 | H18: =MAX(0,ROUND(C18*G18,0))
A19: Colorectal Surgery | B19: Yes | C19: 528 | D19: 467 | E19: =C19-D19 | F19: =D19/C19 | G19: =Inputs!B7-F19 | H19: =MAX(0,ROUND(C19*G19,0))
A20: Breast Surgery | B20: Yes | C20: 471 | D20: 408 | E20: =C20-D20 | F20: =D20/C20 | G20: =Inputs!B7-F20 | H20: =MAX(0,ROUND(C20*G20,0))
A21: Respiratory Medicine | B21: No | C21: 345 | D21: 334 | E21: =C21-D21 | F21: =D21/C21 | G21: =Inputs!B7-F21 | H21: =MAX(0,ROUND(C21*G21,0))
A22: Vascular Surgery | B22: Yes | C22: 227 | D22: 175 | E22: =C22-D22 | F22: =D22/C22 | G22: =Inputs!B7-F22 | H22: =MAX(0,ROUND(C22*G22,0))
A23: Paediatric Service | B23: No | C23: 114 | D23: 110 | E23: =C23-D23 | F23: =D23/C23 | G23: =Inputs!B7-F23 | H23: =MAX(0,ROUND(C23*G23,0))
A24: Interventional Radiology Service | B24: No | C24: 104 | D24: 104 | E24: =C24-D24 | F24: =D24/C24 | G24: =Inputs!B7-F24 | H24: =MAX(0,ROUND(C24*G24,0))
A25: Acute Internal Medicine | B25: No | C25: 53 | D25: 52 | E25: =C25-D25 | F25: =D25/C25 | G25: =Inputs!B7-F25 | H25: =MAX(0,ROUND(C25*G25,0))
A26: General Internal Medicine | B26: No | C26: 48 | D26: 44 | E26: =C26-D26 | F26: =D26/C26 | G26: =Inputs!B7-F26 | H26: =MAX(0,ROUND(C26*G26,0))
A27: Elderly Medicine Service | B27: No | C27: 41 | D27: 39 | E27: =C27-D27 | F27: =D27/C27 | G27: =Inputs!B7-F27 | H27: =MAX(0,ROUND(C27*G27,0))
A28: Midwifery Service | B28: No | C28: 25 | D28: 0 | E28: =C28-D28 | F28: =D28/C28 | G28: =Inputs!B7-F28 | H28: =MAX(0,ROUND(C28*G28,0))
A29: Dermatology | B29: No | C29: 11 | D29: 11 | E29: =C29-D29 | F29: =D29/C29 | G29: =Inputs!B7-F29 | H29: =MAX(0,ROUND(C29*G29,0))
A30: Dietetics Service | B30: No | C30: 10 | D30: 10 | E30: =C30-D30 | F30: =D30/C30 | G30: =Inputs!B7-F30 | H30: =MAX(0,ROUND(C30*G30,0))
A31: Paediatric Urology | B31: No | C31: 8 | D31: 7 | E31: =C31-D31 | F31: =D31/C31 | G31: =Inputs!B7-F31 | H31: =MAX(0,ROUND(C31*G31,0))
A32: Neurology | B32: No | C32: 5 | D32: 5 | E32: =C32-D32 | F32: =D32/C32 | G32: =Inputs!B7-F32 | H32: =MAX(0,ROUND(C32*G32,0))
A33: Endocrinology | B33: No | C33: 5 | D33: 5 | E33: =C33-D33 | F33: =D33/C33 | G33: =Inputs!B7-F33 | H33: =MAX(0,ROUND(C33*G33,0))
A34: Physiotherapy | B34: No | C34: 4 | D34: 4 | E34: =C34-D34 | F34: =D34/C34 | G34: =Inputs!B7-F34 | H34: =MAX(0,ROUND(C34*G34,0))
A35: Emergency Medicine Service | B35: No | C35: 3 | D35: 1 | E35: =C35-D35 | F35: =D35/C35 | G35: =Inputs!B7-F35 | H35: =MAX(0,ROUND(C35*G35,0))
A36: Diabetes Service | B36: No | C36: 2 | D36: 2 | E36: =C36-D36 | F36: =D36/C36 | G36: =Inputs!B7-F36 | H36: =MAX(0,ROUND(C36*G36,0))
A38: Focus surgical/HVLC total | C38: =SUMIF(B4:B1000,"Yes",C4:C1000) | D38: =SUMIF(B4:B1000,"Yes",D4:D1000) | E38: =C38-D38 | F38: =D38/C38 | G38: =Inputs!B7-F38 | H38: =SUMIF(B4:B1000,"Yes",H4:H1000)

Sheet Formula Trace
A1: Formula Trace
A2: Formula cells are highlighted in yellow; assumption cells are highlighted in green.
A3: Output | B3: Formula | C3: Why it is used
A4: Current day cases | B4: Eligible cohort x current day-case rate | C4: Shows how many cases are already day cases at 67.9%
A5: Target day cases | B5: Eligible cohort x target day-case rate | C5: Shows expected day cases at 85.7%
A6: Converted cases | B6: Eligible cohort x (85.7% - 67.9%) | C6: The improvement converts ordinary elective cases into day cases
A7: Financial efficiency low | B7: Converted cases x 1 bed day x GBP350 | C7: Minimum bed-day cost-avoidance case
A8: Financial efficiency high | B8: Converted cases x 2.18 bed days x GBP350 | C8: Higher case using observed LoS proxy
A9: Waiting list impact low | B9: 0 | C9: Day-case conversion does not automatically reduce RTT backlog
A10: Waiting list impact high | B10: Converted cases | C10: If released bed capacity is fully reinvested, each converted case can support one RTT pathway
A11: Income potential high | B11: Converted cases x income per case proxy | C11: Only applies if extra activity is delivered
A12: Specialty day-case rate | B12: Day cases / eligible elective spells | C12: Uses Patient classification from Inpatients.csv
A13: Income proxy | B13: Derived income per additional case proxy | C13: £577,787 / 5,539 = c.£104.31 per additional case | D13: Source values come from the same user-shared utilisation/cash-up model scenario. This proxy is for gross income potential only, not a confirmed tariff or cost saving.
