Workbook

Sheet Summary
A1: Financial and Backlog Summary
A2: Formulas are retained in the workbook so the logic can be traced and updated.
A3: Initiative | B3: Baseline | C3: What if | D3: Metric | E3: Backlog | F3: Financial Efficiency Opportunity Low | G3: Financial Efficiency Opportunity High | H3: Waiting List Impact Low | I3: Waiting List Impact High | J3: Income Potential Low | K3: Income Potential High | L3: Evidence / notes
A4: Utilisation and Scheduling - no job-planned sessions | B4: 82%-85% utilisation range with 50% job-plan component in original table | C4: Remove job-planned session cases from the range | D4: =TEXT('Util Job Plans'!B11,"#,##0")&" - "&TEXT('Util Job Plans'!B12,"#,##0")&" cases" | E4: =Inputs!B4 | F4: ='Util Job Plans'!B15 | G4: ='Util Job Plans'!B16 | H4: ='Util Job Plans'!B20 | I4: ='Util Job Plans'!B21 | J4: ='Util Job Plans'!B29 | K4: ='Util Job Plans'!B30 | L4: Uses 82%-85% utilisation range and removes the 2,729 case 50% job-plan component.
A5: Utilisation and Scheduling - all job-planned sessions delivered | B5: 82%-85% utilisation range with 50% job-plan component in original table | C5: Add the remaining 50% job-planned session cases | D5: =TEXT('Util Job Plans'!B13,"#,##0")&" - "&TEXT('Util Job Plans'!B14,"#,##0")&" cases" | E5: =Inputs!B4 | F5: ='Util Job Plans'!B17 | G5: ='Util Job Plans'!B18 | H5: ='Util Job Plans'!B22 | I5: ='Util Job Plans'!B23 | J5: ='Util Job Plans'!B31 | K5: ='Util Job Plans'!B32 | L5: Uses 82%-85% utilisation range and adds 2,729 cases to move from 50% to all job-planned sessions delivered.
A6: Day Case Improvement | B6: Current day-case rate 67.9% on example eligible cohort | C6: Move to national median 85.7% | D6: =TEXT('Day Case'!B10,"#,##0")&" converted cases" | E6: =Inputs!B4 | F6: ='Day Case'!B14 | G6: ='Day Case'!B15 | H6: ='Day Case'!B17 | I6: ='Day Case'!B18 | J6: ='Day Case'!B22 | K6: ='Day Case'!B23 | L6: Financial range is avoided bed-day cost. Waiting-list high assumes released bed capacity is fully reinvested into RTT activity.
A7: HVLC On-Site Lists | B7: HVLC cases mixed into general lists; no dedicated ring-fenced sessions | C7: Dedicated HVLC lists across T&O, Ophthalmology, ENT and General Surgery | D7: =TEXT(HVLC!B4,"#,##0")&" - "&TEXT(HVLC!B5,"#,##0")&" additional cases/year" | E7: =Inputs!B4 | F7: =HVLC!B11 | G7: =HVLC!B12 | H7: =HVLC!B14 | I7: =HVLC!B15 | J7: =HVLC!B21 | K7: =HVLC!B22 | L7: Financial columns show net after GBP 18k setup cost. Gross benefit is shown on the HVLC tab.
A8: Estate Utilisation | B8: 78% estate utilisation; 3,361 elective sessions; 7,856 cases | C8: Improve estate utilisation to 85%-90% | D8: =TEXT('Estate Utilisation'!B10,"#,##0")&" - "&TEXT('Estate Utilisation'!B11,"#,##0")&" extra sessions; "&TEXT('Estate Utilisation'!B12,"#,##0")&" - "&TEXT('Estate Utilisation'!B13,"#,##0")&" extra cases" | E8: =Inputs!B4 | F8: ='Estate Utilisation'!B27 | G8: ='Estate Utilisation'!B28 | H8: ='Estate Utilisation'!B15 | I8: ='Estate Utilisation'!B16 | J8: ='Estate Utilisation'!B25 | K8: ='Estate Utilisation'!B26 | L8: Financial columns show net income less marginal session cost. Income columns show gross income at GBP 250 per case.

Sheet Inputs
A1: Shared Inputs
A2: Formulas are retained in the workbook so the logic can be traced and updated.
A3: Input | B3: Value | C3: Unit / note
A4: RTT backlog baseline | B4: 23086 | C4: Opening backlog used across calculations
A5: Day case eligible cohort | B5: 14700 | C5: Example eligible surgical cohort; replace if the 67.9% denominator differs
A6: Current day case rate | B6: 0.679 | C6: Current rate from updated scenario
A7: Target day case rate | B7: 0.857 | C7: National median from updated scenario
A8: Bed day cost | B8: 350 | C8: GBP per bed day
A9: Low bed days avoided per conversion | B9: 1 | C9: Minimum assumption
A10: High bed days avoided per conversion | B10: 2.18 | C10: Observed ordinary elective LoS proxy used for high case
A11: Source income value from previous utilisation model | B11: 577787 | C11: Definition: total extra-case income value (£577,787) from the user-shared utilisation/cash-up model. It is used only as an indicative gross income basis for extra cases/procedures, not as a confirmed tariff or a staff-cost saving.
A12: Source extra cases from same previous model | B12: 5539 | C12: Definition: extra-case volume (5,539) attached to the same source income value. This keeps the income numerator and case denominator from the same source scenario.
A13: Derived income per additional case proxy | B13: =B11/B12 | C13: Definition: average indicative income per extra case = £577,787 / 5,539 = c.£104.31. This is a proxy used only for income potential where additional activity is delivered; it should be replaced with an agreed tariff, income or contribution value if Finance provides one.
A14: HVLC additional cases low | B14: 300 | C14: Dedicated HVLC lists lower estimate
A15: HVLC additional cases high | B15: 500 | C15: Dedicated HVLC lists higher estimate
A16: HVLC gross benefit high | B16: 220000 | C16: Annual financial benefit at 500 cases
A17: HVLC setup cost | B17: 18000 | C17: Investment required
A18: Estate current utilisation | B18: 0.78 | C18: Current estate utilisation assumption
A19: Estate target utilisation low | B19: 0.85 | C19: Low what-if
A20: Estate target utilisation high | B20: 0.9 | C20: High what-if
A21: Estate baseline elective sessions | B21: 3361 | C21: Actual elective sessions from theatre extract
A22: Estate baseline elective cases | B22: 7856 | C22: Completed elective cases from theatre extract
A23: Estate marginal session cost | B23: 500 | C23: GBP per additional session
A24: Theatre income per case | B24: 250 | C24: App theatre income proxy per additional case
A25: Util low cases at 50pct job plan | B25: 4700 | C25: Source scenario: user-shared cash-up model; utilisation at 82%, HVLC improvement 20%, under-utilised job plans included at 50%.
... A29: 50pct job-plan case component | B29: 2729 | C29: Source from user-shared cash-up model: 50% under-utilised job-plan case component used to build no-job-plan and all-job-plan sensitivities.

Sheet Util Job Plans
A1: Utilisation and Job-Plan Sensitivity Workings
A2: Formulas are retained in the workbook so the logic can be traced and updated.
A3: Step | B3: Value | C3: Formula / source
A4: Low utilisation case volume at 50pct job plan | B4: =Inputs!B25 | C4: Source scenario: Cash-up model, utilisation at 82%, HVLC improvement 20%, under-utilised job plans included at 50%; extra cases = 4,700.
A5: High utilisation case volume at 50pct job plan | B5: =Inputs!B26 | C5: Source scenario: Cash-up model, utilisation at 85%, HVLC improvement 30%, under-utilised job plans included at 50%; extra cases = 5,539.
A6: Low financial value at 50pct job plan | B6: =Inputs!B27 | C6: Source scenario financial impact/WLI reduction from user-shared cash-up table: utilisation 82% + HVLC 20% + 50% under-utilised job plans = £957,399.03 for 4,700 cases.
A7: High financial value at 50pct job plan | B7: =Inputs!B28 | C7: Source scenario financial impact/WLI reduction from user-shared cash-up table: utilisation 85% + HVLC 30% + 50% under-utilised job plans = £1,117,353.45 for 5,539 cases.
A8: Low financial value per case | B8: =B6/B4 | C8: Derived check: £957,399.03 / 4,700 cases = financial value per case for the low utilisation scenario.
A9: High financial value per case | B9: =B7/B5 | C9: Derived check: £1,117,353.45 / 5,539 cases = financial value per case for the high utilisation scenario.
A10: 50pct job-plan case component | B10: =Inputs!B29 | C10: Source from user-shared model: 2,729 cases is the 50% under-utilised job-plan case component. It is subtracted for the no-job-plan scenario and added again for the all-job-plan scenario.
A11: No job-plan cases low | B11: =B4-B10 | C11: Remove 50pct job-plan component from low scenario
A12: No job-plan cases high | B12: =B5-B10 | C12: Remove 50pct job-plan component from high scenario
A13: All job-plan cases low | B13: =B4+B10 | C13: Add another 50pct job-plan component to represent full delivery
A14: All job-plan cases high | B14: =B5+B10 | C14: Add another 50pct job-plan component to represent full delivery
A15: No job-plan financial low | B15: =B11*B8 | C15: No job-plan low cases x low financial value per case
A16: No job-plan financial high | B16: =B12*B9 | C16: No job-plan high cases x high financial value per case
A17: All job-plan financial low | B17: =B13*B8 | C17: All job-plan low cases x low financial value per case
A18: All job-plan financial high | B18: =B14*B9 | C18: All job-plan high cases x high financial value per case
A19: Backlog baseline | B19: =Inputs!B4 | C19: Opening RTT backlog
A20: No job-plan waiting list impact low | B20: =B11 | C20: Assumes one additional case removes one RTT pathway
A21: No job-plan waiting list impact high | B21: =B12 | C21: Assumes one additional case removes one RTT pathway
A22: All job-plan waiting list impact low | B22: =B13 | C22: Assumes one additional case removes one RTT pathway
A23: All job-plan waiting list impact high | B23: =B14 | C23: Assumes one additional case removes one RTT pathway
A24: No job-plan closing backlog low | B24: =B19-B20 | C24: Backlog - no job-plan low impact
A25: No job-plan closing backlog high | B25: =B19-B21 | C25: Backlog - no job-plan high impact
A26: All job-plan closing backlog low | B26: =B19-B22 | C26: Backlog - all job-plan low impact
A27: All job-plan closing backlog high | B27: =B19-B23 | C27: Backlog - all job-plan high impact
A28: Income per case proxy | B28: =Inputs!B13 | C28: Earlier scenario income value / extra cases
A29: No job-plan income low | B29: =B11*B28 | C29: No job-plan low cases x income proxy
A30: No job-plan income high | B30: =B12*B28 | C30: No job-plan high cases x income proxy
A31: All job-plan income low | B31: =B13*B28 | C31: All job-plan low cases x income proxy
A32: All job-plan income high | B32: =B14*B28 | C32: All job-plan high cases x income proxy
A35: Source note | B35: The 50pct job-plan financial values are source values from the user-shared cash-up model, not values generated from the staff-cost file. They represent financial impact/WLI reduction for the base scenarios before the no-job-plan and all-job-plan sensitivity adjustments.

Sheet Day Case
A1: Day Case Improvement Workings
A2: Formulas are retained in the workbook so the logic can be traced and updated.
A3: Step | B3: Value | C3: Formula / source
A4: Eligible case cohort | B4: =Inputs!B5 | C4: Input: eligible surgical cohort
A5: Current day case rate | B5: =Inputs!B6 | C5: Input
A6: Target day case rate | B6: =Inputs!B7 | C6: Input
A7: Rate improvement | B7: =B6-B5 | C7: Target rate - current rate
A8: Current day cases | B8: =B4*B5 | C8: Eligible cases x current rate
A9: Target day cases | B9: =B4*B6 | C9: Eligible cases x target rate
A10: Converted overnight cases / additional day cases | B10: =B4*B7 | C10: Eligible cases x rate improvement
A11: Bed day cost | B11: =Inputs!B8 | C11: GBP per bed day
A12: Low bed days avoided per conversion | B12: =Inputs!B9 | C12: Minimum assumption
A13: High bed days avoided per conversion | B13: =Inputs!B10 | C13: Observed LoS proxy
A14: Financial efficiency low | B14: =B10*B12*B11 | C14: Converted cases x low bed days x bed day cost
A15: Financial efficiency high | B15: =B10*B13*B11 | C15: Converted cases x high bed days x bed day cost
A16: Backlog baseline | B16: =Inputs!B4 | C16: Opening RTT backlog
A17: Waiting list impact low | B17: =0 | C17: No automatic backlog reduction unless capacity is reinvested
A18: Waiting list impact high | B18: =B10 | C18: One converted case creates capacity for one RTT pathway
A19: Backlog reduction high % | B19: =B18/B16 | C19: High impact / backlog
A20: Closing backlog high | B20: =B16-B18 | C20: Backlog - high waiting list impact
A21: Income per case proxy | B21: =Inputs!B13 | C21: Earlier scenario income value / extra cases
A22: Income potential low | B22: =0 | C22: No extra activity delivered
A23: Income potential high | B23: =B10*B21 | C23: Converted cases x income per case proxy

Sheet HVLC
A1: HVLC Workings
A2: Formulas are retained in the workbook so the logic can be traced and updated.
A3: Step | B3: Value | C3: Formula / source
A4: Additional cases low | B4: =Inputs!B14 | C4: Input from HVLC opportunity range
A5: Additional cases high | B5: =Inputs!B15 | C5: Input from HVLC opportunity range
A6: Gross benefit at high case estimate | B6: =Inputs!B16 | C6: Annual financial benefit at 500 cases
A7: Gross benefit per case | B7: =B6/B5 | C7: Gross benefit / high additional cases
A8: Gross financial benefit low | B8: =B4*B7 | C8: Low cases x benefit per case
A9: Gross financial benefit high | B9: =B5*B7 | C9: High cases x benefit per case
A10: Setup cost | B10: =Inputs!B17 | C10: Investment required
A11: Net financial opportunity low | B11: =B8-B10 | C11: Gross low - setup cost
A12: Net financial opportunity high | B12: =B9-B10 | C12: Gross high - setup cost
A13: Backlog baseline | B13: =Inputs!B4 | C13: Opening RTT backlog
A14: Waiting list impact low | B14: =B4 | C14: Low additional cases
A15: Waiting list impact high | B15: =B5 | C15: High additional cases
A16: Backlog reduction low % | B16: =B14/B13 | C16: Low impact / backlog
A17: Backlog reduction high % | B17: =B15/B13 | C17: High impact / backlog
A18: Closing backlog low | B18: =B13-B14 | C18: Backlog - low impact
A19: Closing backlog high | B19: =B13-B15 | C19: Backlog - high impact
A20: Income per case proxy | B20: =Inputs!B13 | C20: Earlier scenario income value / extra cases
A21: Income potential low | B21: =B4*B20 | C21: Low cases x income proxy
A22: Income potential high | B22: =B5*B20 | C22: High cases x income proxy

Sheet Estate Utilisation
A1: Estate Utilisation Workings
A2: Formulas are retained in the workbook so the logic can be traced and updated.
A3: Step | B3: Value | C3: Formula / source
A4: Current estate utilisation | B4: =Inputs!B18 | C4: Input
A5: Low target utilisation | B5: =Inputs!B19 | C5: Input
A6: High target utilisation | B6: =Inputs!B20 | C6: Input
A7: Baseline elective sessions | B7: =Inputs!B21 | C7: Theatre extract actual elective sessions
A8: Baseline elective cases | B8: =Inputs!B22 | C8: Theatre extract completed elective cases
A9: Cases per session | B9: =B8/B7 | C9: Baseline cases / baseline sessions
A10: Extra sessions low | B10: =B7*((B5/B4)-1) | C10: Sessions x ((low target/current utilisation)-1)
A11: Extra sessions high | B11: =B7*((B6/B4)-1) | C11: Sessions x ((high target/current utilisation)-1)
A12: Extra cases low | B12: =B10*B9 | C12: Extra sessions low x cases per session
A13: Extra cases high | B13: =B11*B9 | C13: Extra sessions high x cases per session
A14: Backlog baseline | B14: =Inputs!B4 | C14: Opening RTT backlog
A15: Waiting list impact low | B15: =B12 | C15: One additional case removes one RTT pathway
A16: Waiting list impact high | B16: =B13 | C16: One additional case removes one RTT pathway
A17: Backlog reduction low % | B17: =B15/B14 | C17: Low impact / backlog
A18: Backlog reduction high % | B18: =B16/B14 | C18: High impact / backlog
A19: Closing backlog low | B19: =B14-B15 | C19: Backlog - low impact
A20: Closing backlog high | B20: =B14-B16 | C20: Backlog - high impact
A21: Marginal session cost | B21: =Inputs!B23 | C21: GBP per additional session
A22: Cost low | B22: =B10*B21 | C22: Extra sessions low x marginal session cost
A23: Cost high | B23: =B11*B21 | C23: Extra sessions high x marginal session cost
A24: Theatre income per case | B24: =Inputs!B24 | C24: App theatre income proxy
A25: Income potential low | B25: =B12*B24 | C25: Extra cases low x income per case
A26: Income potential high | B26: =B13*B24 | C26: Extra cases high x income per case
A27: Net financial opportunity low | B27: =B25-B22 | C27: Income low - cost low
A28: Net financial opportunity high | B28: =B26-B23 | C28: Income high - cost high

Sheet Formula Trace
A1: Formula Trace
A2: Formulas are retained in the workbook so the logic can be traced and updated.
A3: Initiative | B3: Output | C3: Formula | D3: Source / note
A4: Util Job Plans | B4: Low financial value at 50pct job plan | C4: Source value, not recalculated: £957,399.03 | D4: User-shared cash-up model scenario: utilisation 82%, HVLC improvement 20%, under-utilised job plans at 50%, 4,700 cases. Used as the low financial impact/WLI-reduction baseline.
A5: Util Job Plans | B5: High financial value at 50pct job plan | C5: Source value, not recalculated: £1,117,353.45 | D5: User-shared cash-up model scenario: utilisation 85%, HVLC improvement 30%, under-utilised job plans at 50%, 5,539 cases. Used as the high financial impact/WLI-reduction baseline.
A6: Util Job Plans | B6: Low financial value per case | C6: £957,399.03 / 4,700 | D6: Derived only to allow sensitivity modelling after removing or adding the job-plan case component.
A7: Util Job Plans | B7: High financial value per case | C7: £1,117,353.45 / 5,539 | D7: Derived only to allow sensitivity modelling after removing or adding the job-plan case component.
A8: Util Job Plans | B8: No job-plan cases | C8: Original 50% job-plan case range - 2,729 cases | D8: Low 4,700 - 2,729; high 5,539 - 2,729
A9: Util Job Plans | B9: All job-plan cases | C9: Original 50% job-plan case range + 2,729 cases | D9: Low 4,700 + 2,729; high 5,539 + 2,729
A10: Util Job Plans | B10: Financial range | C10: Adjusted cases x scenario-specific financial value per case | D10: Financial value per case derived from earlier table
A11: Util Job Plans | B11: Income range | C11: Adjusted cases x income per case proxy | D11: Income per case proxy = GBP577,787 / 5,539
A12: Day Case | B12: Converted cases | C12: Eligible cohort x (target day-case rate - current day-case rate) | D12: 14,700 x (85.7% - 67.9%)
A13: Day Case | B13: Financial low | C13: Converted cases x 1 bed day x GBP350 | D13: Minimum bed-day avoided assumption
A14: Day Case | B14: Financial high | C14: Converted cases x 2.18 bed days x GBP350 | D14: Uses observed ordinary elective LoS proxy
... A28: Income proxy | B28: Derived income per additional case proxy | C28: £577,787 / 5,539 = c.£104.31 per additional case | D28: Source values come from the same user-shared utilisation/cash-up model scenario. This proxy is for gross income potential only, not a confirmed tariff or cost saving.
