Workbook

Sheet Summary
A1: BADS Day Case / Outpatient Improvement Summary
A2: Formula cells are highlighted in yellow; assumptions/source values are highlighted in green.
A3: Initiative | B3: Baseline | C3: What if | D3: Metric | E3: Backlog | F3: Financial Efficiency Opportunity Low | G3: Financial Efficiency Opportunity High | H3: Waiting List Impact Low | I3: Waiting List Impact High | J3: Income Potential Low | K3: Income Potential High | L3: Evidence / caveat
A4: BADS day case and outpatient improvement | B4: Model Hospital BADS All baseline: 67.9% | C4: Move to 85.7% | D4: =TEXT('Worked Calculation'!B6,"0.0%")&" improvement; "&TEXT('Worked Calculation'!B10,"#,##0")&" shifted procedures" | E4: =Inputs!B7 | F4: ='Worked Calculation'!B17 | G4: ='Worked Calculation'!B18 | H4: ='Worked Calculation'!B19 | I4: ='Worked Calculation'!B20 | J4: ='Worked Calculation'!B24 | K4: ='Worked Calculation'!B25 | L4: Uses 14,700 as a proxy denominator. Replace with actual Model Hospital BADS total procedures when available.

Sheet Inputs
A1: Inputs
A2: Formula cells are highlighted in yellow; assumptions/source values are highlighted in green.
A3: Input / source value | B3: Value | C3: Source / note
A4: Model Hospital BADS All baseline | B4: 0.679 | C4: BADS All: day case and outpatient % of total procedures: inpatient + day case + outpatient
A5: What-if target | B5: 0.857 | C5: National median / target supplied
A6: Procedure denominator proxy | B6: 14700 | C6: Proxy denominator used for current scenario until actual Model Hospital BADS total procedure count is available
A7: Opening RTT backlog | B7: 23086 | C7: Backlog baseline used in the opportunity tables
A8: Bed-day cost | B8: 350 | C8: Cost avoidance assumption: GBP350 per bed day
A9: Low bed days avoided per shifted procedure | B9: 1 | C9: Minimum assumption
A10: High bed days avoided per shifted procedure | B10: 2.18 | C10: Observed ordinary elective LoS proxy used for high case
A11: Source income value from previous utilisation model | B11: 577787 | C11: Definition: total extra-case income value (£577,787) from the user-shared utilisation/cash-up model. It is used only as an indicative gross income basis for extra cases/procedures, not as a confirmed tariff or a staff-cost saving.
A12: Source extra cases from same previous model | B12: 5539 | C12: Definition: extra-case volume (5,539) attached to the same source income value. This keeps the income numerator and case denominator from the same source scenario.
A13: Derived income per additional case proxy | B13: =B11/B12 | C13: Definition: average indicative income per extra case = £577,787 / 5,539 = c.£104.31. This is a proxy used only for income potential where additional activity is delivered; it should be replaced with an agreed tariff, income or contribution value if Finance provides one.

Sheet Worked Calculation
A1: Worked Calculation
A2: Formula cells are highlighted in yellow; assumptions/source values are highlighted in green.
A3: Step | B3: Value | C3: Formula / explanation
A4: Baseline BADS rate | B4: =Inputs!B4 | C4: Model Hospital BADS All baseline
A5: Target BADS rate | B5: =Inputs!B5 | C5: What-if target
A6: Rate improvement | B6: =B5-B4 | C6: Target rate - baseline rate
A7: Procedure denominator proxy | B7: =Inputs!B6 | C7: Total BADS procedures proxy: inpatient + day case + outpatient
A8: Baseline day case + outpatient procedures | B8: =B7*B4 | C8: Denominator x baseline rate
A9: Target day case + outpatient procedures | B9: =B7*B5 | C9: Denominator x target rate
A10: Shifted procedures / additional day case or outpatient activity | B10: =B7*B6 | C10: Denominator x rate improvement
A11: Opening RTT backlog | B11: =Inputs!B7 | C11: Backlog baseline
A12: Low bed days avoided per shifted procedure | B12: =Inputs!B9 | C12: Low assumption
A13: High bed days avoided per shifted procedure | B13: =Inputs!B10 | C13: High assumption
A14: Bed-day cost | B14: =Inputs!B8 | C14: GBP per bed day
A15: Avoided bed days low | B15: =B10*B12 | C15: Shifted procedures x low bed-day assumption
A16: Avoided bed days high | B16: =B10*B13 | C16: Shifted procedures x high bed-day assumption
A17: Financial efficiency low | B17: =B15*B14 | C17: Avoided bed days low x bed-day cost
A18: Financial efficiency high | B18: =B16*B14 | C18: Avoided bed days high x bed-day cost
A19: Waiting list impact low | B19: =0 | C19: No automatic RTT reduction unless released capacity is reinvested
A20: Waiting list impact high | B20: =B10 | C20: If fully reinvested: one shifted procedure supports one RTT pathway
A21: Backlog reduction high % | B21: =B20/B11 | C21: Waiting-list impact high / opening RTT backlog
A22: Closing backlog high | B22: =B11-B20 | C22: Opening RTT backlog - waiting-list impact high
A23: Income per case proxy | B23: =Inputs!B13 | C23: Derived proxy: source income value (£577,787) divided by source extra cases (5,539), giving c.£104.31 per additional case.
A24: Income potential low | B24: =0 | C24: No additional activity delivered
A25: Income potential high | B25: =B10*B23 | C25: Shifted / additional cases x derived income per case proxy. This is a gross income-potential lens only and applies only if capacity is used to deliver extra activity.

Sheet Formula Trace
A1: Formula Trace
A2: Formula cells are highlighted in yellow; assumptions/source values are highlighted in green.
A3: Output | B3: Formula | C3: Explanation
A4: BADS baseline | B4: 67.9% | C4: Model Hospital BADS All: day case and outpatient % of total procedures, where total procedures = inpatient + day case + outpatient.
A5: Target | B5: 85.7% | C5: What-if target / national median supplied.
A6: Rate improvement | B6: 85.7% - 67.9% = 17.8 percentage points | C6: Shows the proportion of procedures shifted into day case/outpatient setting.
A7: Shifted procedures | B7: Procedure denominator proxy x 17.8% | C7: Uses 14,700 proxy denominator until actual Model Hospital BADS procedure denominator is available.
A8: Financial efficiency low | B8: Shifted procedures x 1 bed day x GBP350 | C8: Low cost-avoidance assumption.
A9: Financial efficiency high | B9: Shifted procedures x 2.18 bed days x GBP350 | C9: High cost-avoidance assumption using LoS proxy.
A10: Waiting list impact low | B10: 0 | C10: No automatic backlog reduction from setting shift unless capacity is reinvested.
A11: Waiting list impact high | B11: Shifted procedures | C11: Assumes every shifted procedure releases capacity for one RTT pathway.
A12: Income potential high | B12: Shifted procedures x income per case proxy | C12: Income proxy = GBP577,787 / 5,539.
A13: Income proxy | B13: Derived income per additional case proxy | C13: £577,787 / 5,539 = c.£104.31 per additional case | D13: Source values come from the same user-shared utilisation/cash-up model scenario. This proxy is for gross income potential only, not a confirmed tariff or cost saving.
