Workbook

Sheet Summary Table
A1: HVLC Financial and Backlog Impact Summary
A2: Cells in green contain live Excel formulas. The calculation tabs show the trace behind each summary statement.
A4: # | B4: Initiative | C4: Aim / data basis | D4: Financial Benefit | E4: Backlog Impact | F4: Trace
A5: 5 | B5: HVLC On-Site Lists Overview | C5: Dedicated HVLC lists across T&O, Ophthalmology, ENT and General Surgery; estimated 300-500 additional cases/year. | D5: ="Based on "&TEXT('HVLC Overview'!B4,"#,##0")&"-"&TEXT('HVLC Overview'!C4,"#,##0")&" additional cases/year, financial opportunity is "&TEXT('HVLC Overview'!G4,"£#,##0")&"-"&TEXT('HVLC Overview'!H4,"£#,##0")&" WLI-equivalent reduction." | E5: ="Reduces RTT backlog from "&TEXT('HVLC Overview'!I4,"#,##0")&" to "&TEXT('HVLC Overview'!K4,"#,##0")&"-"&TEXT('HVLC Overview'!J4,"#,##0")&", a reduction of "&TEXT('HVLC Overview'!B4,"#,##0")&"-"&TEXT('HVLC Overview'!C4,"#,##0")&" pathways ("&TEXT('HVLC Overview'!L4,"0.0%")&"-"&TEXT('HVLC Overview'!M4,"0.0%")&")." | F5: See HVLC Overview rows 4-5 and Formula Trace rows 4-6.
A6: 6 | B6: T&O Hip/Knee | C6: Theatre activity identifies elective hip/knee procedure cases; target is 4 joint replacements per all-day list. | D6: ="Indicative WLI-equivalent opportunity: "&TEXT('Procedure Activity'!M4,"£#,##0")&"/year, based on moving from "&TEXT('Procedure Activity'!E4,"0.0")&" to "&TEXT('Procedure Activity'!I4,"0.0")&" cases/list." | E6: ="Specialty-level proxy: "&TEXT('Procedure Activity'!K4,"#,##0")&" additional cases/year against T&O backlog of "&TEXT('Procedure Activity'!B4,"#,##0")&", reducing backlog to "&TEXT('Procedure Activity'!N4,"#,##0")&" ("&TEXT('Procedure Activity'!O4,"0.0%")&")." | F6: See Procedure Activity row 4 and Formula Trace rows 8-12.
A7: 7 | B7: T&O Hand/Wrist | C7: Theatre activity identifies elective hand/wrist procedure cases; target is 6 cases per dedicated list. | D7: ="Indicative WLI-equivalent opportunity: "&TEXT('Procedure Activity'!M5,"£#,##0")&"/year, based on moving from "&TEXT('Procedure Activity'!E5,"0.0")&" to "&TEXT('Procedure Activity'!I5,"0.0")&" cases/list." | E7: ="Specialty-level proxy: "&TEXT('Procedure Activity'!K5,"#,##0")&" additional cases/year against T&O backlog of "&TEXT('Procedure Activity'!B5,"#,##0")&", reducing backlog to "&TEXT('Procedure Activity'!N5,"#,##0")&" ("&TEXT('Procedure Activity'!O5,"0.0%")&")." | F7: See Procedure Activity row 5 and Formula Trace rows 8-12.
A8: 8 | B8: Ophthalmology Cataract | C8: Theatre activity identifies elective cataract procedure cases; target is 10 cataracts per 4-hour list and >=36 cases/week. | D8: ="Indicative WLI-equivalent opportunity: "&TEXT('Procedure Activity'!M6,"£#,##0")&"/year, based on moving from "&TEXT('Procedure Activity'!F6,"#,##0")&" to "&TEXT('Procedure Activity'!J6,"#,##0")&" cases/year." | E8: ="Specialty-level proxy: "&TEXT('Procedure Activity'!K6,"#,##0")&" additional cases/year against Ophthalmology backlog of "&TEXT('Procedure Activity'!B6,"#,##0")&", reducing backlog to "&TEXT('Procedure Activity'!N6,"#,##0")&" ("&TEXT('Procedure Activity'!O6,"0.0%")&")." | F8: See Procedure Activity row 6 and Formula Trace rows 8-12.

Sheet Inputs
A1: HVLC Financial and Backlog Model - Inputs
A3: Input | B3: Value | C3: Unit | D3: Source / note
A4: Baseline RTT backlog | B4: 23086 | C4: pathways | D4: Total specialty backlog from shared opportunity table
A5: T&O specialty backlog | B5: 5203 | C5: pathways | D5: Trauma & Orthopaedics backlog from shared opportunity table
A6: Ophthalmology specialty backlog | B6: 3084 | C6: pathways | D6: Ophthalmology backlog from shared opportunity table
A7: WLI sessions | B7: 2673 | C7: sessions | D7: Total WLI sessions from shared opportunity table
A8: WLI spend | B8: 1336600 | C8: GBP | D8: Total WLI spend from shared opportunity table
A9: WLI cost per session | B9: =B8/B7 | C9: GBP/session | D9: Formula: WLI spend / WLI sessions
A10: Theatre source start date | B10: 45017 | C10: date | D10: data/raw/theatre utilisation/Upload - Theatres Activity Apr 23 - Mar 26 v2.csv
A11: Theatre source end date | B11: 46112 | C11: date | D11: data/raw/theatre utilisation/Upload - Theatres Activity Apr 23 - Mar 26 v2.csv
A12: Theatre source period years | B12: =(B11-B10+1)/365.25 | C12: years | D12: Formula: inclusive date range / 365.25
A13: HVLC lower additional cases | B13: 300 | C13: cases/year | D13: Dedicated HVLC list assumption from Opportunity model
A14: HVLC upper additional cases | B14: 500 | C14: cases/year | D14: Dedicated HVLC list assumption from Opportunity model
A15: HVLC modelled improvement cases | B15: 462 | C15: cases/year | D15: Modelled HVLC improvement from shared table
A16: HVLC average cases per list | B16: 2 | C16: cases/list | D16: Used to convert additional cases into WLI-equivalent sessions
A17: Hip/knee target cases per list | B17: 4 | C17: cases/list | D17: GIRFT target in user table
A18: Hand/wrist target cases per list | B18: 6 | C18: cases/list | D18: Dedicated list target in user table
A19: Cataract target cases per week | B19: 36 | C19: cases/week | D19: User table: >=36 cases/week
A20: Cataract target cases per list | B20: 10 | C20: cases/list | D20: User table: 10 cataracts per 4-hour list

Sheet Procedure Activity
A1: Procedure Activity and Proxy Backlog Calculation
A3: Procedure group | B3: Specialty backlog proxy | C3: Completed cases in source period | D3: Sessions in source period | E3: Current cases per list | F3: Current cases per year | G3: Sessions per year | H3: Target basis | I3: Target cases per list | J3: Target cases per year | K3: Additional cases per year | L3: WLI-equivalent sessions per year | M3: Financial opportunity per year | N3: Remaining specialty backlog proxy | O3: Backlog reduction % proxy | P3: Top matched procedure descriptions | Q3: Formula trace
A4: T&O hip/knee | B4: =Inputs!B5 | C4: 1763 | D4: 925 | E4: =C4/D4 | F4: =C4/Inputs!B12 | G4: =D4/Inputs!B12 | H4: 4 joint replacements/all-day list | I4: =Inputs!B17 | J4: =G4*I4 | K4: =MAX(J4-F4,0) | L4: =K4/I4 | M4: =L4*Inputs!B9 | N4: =B4-K4 | O4: =K4/B4 | P4: Primary total prosthetic replacement of knee joint using cement; Primary total prosthetic replacement of knee joint using cement (S); Primary total prosthetic replacement of hip joint using cement; Primary total prosthetic replacement of hip joint using cement (S); Primary total prosthetic replacement of knee joint NEC (S) | Q4: Additional cases/year = max((sessions/year * target cases/list) - current cases/year, 0). Backlog % uses total T&O backlog because procedure-level backlog is not available.
A5: T&O hand/wrist | B5: =Inputs!B5 | C5: 288 | D5: 154 | E5: =C5/D5 | F5: =C5/Inputs!B12 | G5: =D5/Inputs!B12 | H5: 6 hand/wrist cases/dedicated list | I5: =Inputs!B18 | J5: =G5*I5 | K5: =MAX(J5-F5,0) | L5: =K5/I5 | M5: =L5*Inputs!B9 | N5: =B5-K5 | O5: =K5/B5 | P5: Carpal tunnel release; Carpal tunnel release (S); Hand NEC; Finger NEC; Wrist NEC | Q5: Additional cases/year = max((sessions/year * target cases/list) - current cases/year, 0). Backlog % uses total T&O backlog because procedure-level backlog is not available.
A6: Ophthalmology cataract | B6: =Inputs!B6 | C6: 2766 | D6: 883 | E6: =C6/D6 | F6: =C6/Inputs!B12 | G6: =D6/Inputs!B12 | H6: >=36 cases/week and 10 cataracts/4-hour list | I6: =Inputs!B20 | J6: =Inputs!B19*52 | K6: =MAX(J6-F6,0) | L6: =K6/I6 | M6: =L6*Inputs!B9 | N6: =B6-K6 | O6: =K6/B6 | P6: Phacoemulsification of lens; Phacoemulsification of lens (S); Insertion of prosthetic replacement for lens NEC (S); Discission of cataract; Discission of cataract (S) | Q6: Additional cases/year = max((36 cases/week * 52) - current cases/year, 0). Financial converts additional cases to 10-case lists. Backlog % uses total Ophthalmology backlog because cataract-level backlog is not available.

Sheet HVLC Overview
A1: HVLC On-Site Lists Overview - Range Calculation
A3: Scenario | B3: Additional cases lower | C3: Additional cases upper | D3: Cases per list | E3: WLI sessions avoided lower | F3: WLI sessions avoided upper | G3: Financial lower | H3: Financial upper | I3: Baseline backlog | J3: Remaining backlog lower impact | K3: Remaining backlog upper impact | L3: Backlog reduction lower % | M3: Backlog reduction upper % | N3: Formula trace
A4: Dedicated HVLC lists - range | B4: =Inputs!B13 | C4: =Inputs!B14 | D4: =Inputs!B16 | E4: =B4/D4 | F4: =C4/D4 | G4: =E4*Inputs!B9 | H4: =F4*Inputs!B9 | I4: =Inputs!B4 | J4: =I4-B4 | K4: =I4-C4 | L4: =B4/I4 | M4: =C4/I4 | N4: Financial = additional cases / cases per list * WLI cost per session; Backlog % = additional cases / baseline RTT backlog
A5: Dedicated HVLC lists - modelled 462 cases | B5: =Inputs!B15 | C5: =Inputs!B15 | D5: =Inputs!B16 | E5: =B5/D5 | F5: =C5/D5 | G5: =E5*Inputs!B9 | H5: =F5*Inputs!B9 | I5: =Inputs!B4 | J5: =I5-B5 | K5: =I5-C5 | L5: =B5/I5 | M5: =C5/I5 | N5: Uses modelled HVLC improvement cases from shared table

Sheet Formula Trace
A1: Formula Trace and Caveats
A3: Area | B3: Metric | C3: Excel formula / method | D3: Purpose / caveat
A4: Inputs | B4: WLI cost per session | C4: =Inputs!B8/Inputs!B7 | D4: Converts WLI spend and WLI sessions into an assumed session cost.
A5: HVLC overview | B5: WLI sessions avoided | C5: =Additional cases / cases per list | D5: Converts the 300-500 additional case range into WLI-equivalent sessions.
A6: HVLC overview | B6: Financial benefit | C6: =WLI sessions avoided * WLI cost per session | D6: Shows WLI-equivalent reduction opportunity, not confirmed cashable saving.
A7: HVLC overview | B7: Remaining backlog | C7: =Baseline RTT backlog - additional cases | D7: Assumes additional cases are all RTT-backlog cases.
A8: HVLC overview | B8: Backlog reduction % | C8: =Additional cases / baseline RTT backlog | D8: Uses total RTT backlog because the HVLC overview is programme-level.
A9: Procedure activity | B9: Current cases per list | C9: =Completed cases / sessions | D9: Uses elective completed theatre activity matched by specialty and procedure text.
A10: Procedure activity | B10: Current cases per year | C10: =Completed cases / theatre source period years | D10: Annualises activity from Apr 2023-Mar 2026 theatre data.
A11: Procedure activity | B11: Target cases per year - hip/knee and hand/wrist | C11: =Sessions per year * target cases per list | D11: Uses current list/session volume and applies the dedicated-list target.
A12: Procedure activity | B12: Target cases per year - cataract | C12: =36 cases/week * 52 | D12: Uses the stated >=36 cataract cases/week aim.
A13: Procedure activity | B13: Additional cases per year | C13: =MAX(Target cases per year - current cases per year, 0) | D13: Estimates incremental procedure capacity.
A14: Procedure activity | B14: Financial opportunity | C14: =Additional cases per year / target cases per list * WLI cost per session | D14: Converts incremental procedure cases into WLI-equivalent sessions.
A15: Procedure activity | B15: Backlog impact % proxy | C15: =Additional cases per year / specialty backlog | D15: Proxy only: current RTT data is by specialty, not procedure.
A16: Caveat | B16: Procedure-level backlog | C16: Not available in current RTT/PTL datasets | D16: RTT extracts have Treatment Function Name only; PTL CSV is overall only.
A17: Caveat | B17: Finance | C17: WLI-equivalent reduction, not confirmed cash release | D17: Finance should confirm cashability, tariff/payment treatment, and whether benefits overlap.
